odoo/addons/l10n_ro_config/README.rst
odoo/addons/l10n_ro_config/__init__.py
odoo/addons/l10n_ro_config/__manifest__.py
odoo/addons/l10n_ro_config/data/res_currency_data.xml
odoo/addons/l10n_ro_config/examples/l10n_ro_hr/hr.job.csv
odoo/addons/l10n_ro_config/examples/l10n_ro_hr/res.company.caen.csv
odoo/addons/l10n_ro_config/examples/l10n_ro_hr_medical_holidays/hr.holidays.status.csv
odoo/addons/l10n_ro_config/examples/l10n_ro_hr_medical_holidays/hr.medical.disease.csv
odoo/addons/l10n_ro_config/examples/l10n_ro_hr_medical_holidays/hr.medical.emergency.disease.csv
odoo/addons/l10n_ro_config/examples/l10n_ro_hr_medical_holidays/hr.medical.infecto.disease.csv
odoo/addons/l10n_ro_config/examples/l10n_ro_siruta/res.city.csv
odoo/addons/l10n_ro_config/examples/l10n_ro_siruta/res.country.commune.csv
odoo/addons/l10n_ro_config/examples/l10n_ro_siruta/res.country.state.csv
odoo/addons/l10n_ro_config/examples/l10n_ro_siruta/res.country.zone.csv
odoo/addons/l10n_ro_config/i18n/l10n_ro_config.pot
odoo/addons/l10n_ro_config/i18n/ro.po
odoo/addons/l10n_ro_config/models/__init__.py
odoo/addons/l10n_ro_config/models/res_config.py
odoo/addons/l10n_ro_config/static/description/icon.png
odoo/addons/l10n_ro_config/views/res_config_view.xml
odoo11_addon_l10n_ro_config-11.0.1.0.0.99.dev8.dist-info/METADATA
odoo11_addon_l10n_ro_config-11.0.1.0.0.99.dev8.dist-info/WHEEL
odoo11_addon_l10n_ro_config-11.0.1.0.0.99.dev8.dist-info/top_level.txt
odoo11_addon_l10n_ro_config-11.0.1.0.0.99.dev8.dist-info/RECORD
